network-dataset/__init__.py
network-dataset/dataset.py
nids_datasets/__init__.py
nids_datasets/dataset.py
nids_datasets-0.1.5.dist-info/METADATA
nids_datasets-0.1.5.dist-info/WHEEL
nids_datasets-0.1.5.dist-info/top_level.txt
nids_datasets-0.1.5.dist-info/RECORD
