Metadata-Version: 2.1
Name: nids-datasets
Version: 0.1.5
Summary: Download and utilize specially curated and extracted datasets from the original UNSW-NB15 and CIC-IDS2017 datasets
Home-page: https://github.com/rdpahalavan/nids-datasets
Author: Pahalavan R D
Author-email: rdpahalavan24@gmail.com
License: Apache License 2.0
Keywords: Dataset NIDS UNSW-NB15 CIC-IDS2017
Classifier: Programming Language :: Python :: 3
Classifier: License :: OSI Approved :: Apache Software License
Classifier: Operating System :: OS Independent
Requires-Python: >=3.7.0
Requires-Dist: datasets (>=2.10.0)
Requires-Dist: huggingface-hub (>=0.16.0)
Requires-Dist: numpy (>=1.20.0)
Requires-Dist: pandas (>=2.0.0)
Requires-Dist: pyarrow (>=12.0.0)
Requires-Dist: tqdm (>=4.50.0)
